{
    "records": [
        {
            "attributes": {
                "type": "Account",
                "referenceId": "AccountRef1"
            },
            "Name": "Hilton Union Square",
            "location__Latitude__s": 37.786164,
            "location__Longitude__s": -122.410137
        },
        {
            "attributes": {
                "type": "Account",
                "referenceId": "AccountRef2"
            },
            "Name": "Marriott Marquis",
            "location__Latitude__s": 37.785143,
            "location__Longitude__s": -122.403405
        },
        {
            "attributes": {
                "type": "Account",
                "referenceId": "AccountRef3"
            },
            "Name": "Hyatt",
            "location__Latitude__s": 37.794157,
            "location__Longitude__s": -122.396311
        }
    ]
}